LICENSE
nonebot_plugin_7s_roll/__init__.py
nonebot_plugin_7s_roll/command.py
nonebot_plugin_7s_roll/common.py
nonebot_plugin_7s_roll/config.py
nonebot_plugin_7s_roll/expr.py
nonebot_plugin_7s_roll/roll.py
nonebot_plugin_7s_roll-0.2.0.dist-info/LICENSE
nonebot_plugin_7s_roll-0.2.0.dist-info/METADATA
nonebot_plugin_7s_roll-0.2.0.dist-info/WHEEL
nonebot_plugin_7s_roll-0.2.0.dist-info/RECORD
