Metadata-Version: 2.1
Name: nonebot-plugin-7s-roll
Version: 0.2.0
Summary: A roll dice plugin for nonebot
Home-page: https://github.com/7sDream/nonebot_plugin_7s_roll
License: MIT
Keywords: nonebot,dice,roll,trpg
Author: 7sDream
Author-email: i@7sdre.am
Requires-Python: >=3.9,<4.0
Classifier: Development Status :: 3 - Alpha
Classifier: Environment :: Plugins
Classifier: License :: OSI Approved :: MIT License
Classifier: Operating System :: OS Independent
Classifier: Programming Language :: Python :: 3
Classifier: Programming Language :: Python :: 3.9
Classifier: Programming Language :: Python :: 3.10
Classifier: Programming Language :: Python :: 3.11
Classifier: Topic :: Software Development :: Libraries :: Python Modules
Requires-Dist: nonebot-adapter-onebot (>=2.2.3,<3.0.0)
Requires-Dist: nonebot2 (>=2.0.0,<3.0.0)
Project-URL: Repository, https://github.com/7sDream/nonebot_plugin_7s_roll
